Metadata-Version: 1.1
Name: asdfg
Version: 0.4
Summary: asdfg_description
Home-page: http://www.example.com
Author: veera
Author-email: veerabhadrarao.uppu@nexiilabs.com
License: UNKNOWN
Download-URL: https://github.com/uvbr/package_creation/archive/0.4.tar.gz
Platform: UNKNOWN
